tidytcells/__init__.py
tidytcells/_query_engine/__init__.py
tidytcells/_query_engine/hla_query_engine.py
tidytcells/_query_engine/homo_sapiens_ig_query_engine.py
tidytcells/_query_engine/homo_sapiens_tr_query_engine.py
tidytcells/_query_engine/mus_musculus_mh_query_engine.py
tidytcells/_query_engine/mus_musculus_tr_query_engine.py
tidytcells/_query_engine/query_engine.py
tidytcells/_query_engine/tr_query_engine.py
tidytcells/_resources/__init__.py
tidytcells/_resources/homosapiens_ig_aa_sequences.json
tidytcells/_resources/homosapiens_ig_synonyms.json
tidytcells/_resources/homosapiens_mh_synonyms.json
tidytcells/_resources/homosapiens_tr_aa_sequences.json
tidytcells/_resources/homosapiens_tr_synonyms.json
tidytcells/_resources/musmusculus_mh_synonyms.json
tidytcells/_resources/musmusculus_tr_aa_sequences.json
tidytcells/_resources/valid_homosapiens_ig.json
tidytcells/_resources/valid_homosapiens_mh.json
tidytcells/_resources/valid_homosapiens_tr.json
tidytcells/_resources/valid_musmusculus_mh.json
tidytcells/_resources/valid_musmusculus_tr.json
tidytcells/_standardized_gene_symbol/__init__.py
tidytcells/_standardized_gene_symbol/standardized_gene_symbol.py
tidytcells/_standardized_gene_symbol/standardized_hla_symbol.py
tidytcells/_standardized_gene_symbol/standardized_homo_sapiens_ig_symbol.py
tidytcells/_standardized_gene_symbol/standardized_homo_sapiens_tr_symbol.py
tidytcells/_standardized_gene_symbol/standardized_ig_symbol.py
tidytcells/_standardized_gene_symbol/standardized_mus_musculus_mh_symbol.py
tidytcells/_standardized_gene_symbol/standardized_mus_musculus_tr_symbol.py
tidytcells/_standardized_gene_symbol/standardized_tr_symbol.py
tidytcells/_utils/__init__.py
tidytcells/_utils/conserved_aa_lookup.py
tidytcells/_utils/parameter.py
tidytcells/_utils/string_cleaning.py
tidytcells/_utils/warnings.py
tidytcells/aa/__init__.py
tidytcells/aa/_standardize.py
tidytcells/ig/__init__.py
tidytcells/ig/_get_aa_sequence.py
tidytcells/ig/_query.py
tidytcells-2.2.0.dist-info/licenses/LICENSE.txt
tidytcells-2.2.0.dist-info/METADATA
tidytcells-2.2.0.dist-info/WHEEL
tidytcells-2.2.0.dist-info/top_level.txt
tidytcells-2.2.0.dist-info/RECORD
