Metadata-Version: 2.4
Name: tidytcells
Version: 2.2.0
Summary: Standardise TR/MH data
Author-email: Yuta Nagano <yutanagano51@proton.me>
Maintainer-email: Yuta Nagano <yutanagano51@proton.me>
Project-URL: Homepage, https://tidytcells.readthedocs.io
Project-URL: Documentation, https://tidytcells.readthedocs.io
Project-URL: Repository, https://github.com/yutanagano/tidytcells
Project-URL: Issues, https://github.com/yutanagano/tidytcells/issues
Keywords: immunology,bioinformatics,TCR,TR,MHC,MH,HLA,T cell,IMGT
Classifier: Development Status :: 5 - Production/Stable
Classifier: Intended Audience :: Science/Research
Classifier: License :: OSI Approved :: MIT License
Classifier: Operating System :: OS Independent
Classifier: Programming Language :: Python :: 3
Classifier: Topic :: Scientific/Engineering :: Bio-Informatics
Requires-Python: >=3.8
License-File: LICENSE.txt
Provides-Extra: dev
Requires-Dist: beautifulsoup4; extra == "dev"
Requires-Dist: build; extra == "dev"
Requires-Dist: odfpy; extra == "dev"
Requires-Dist: pandas; extra == "dev"
Requires-Dist: pip; extra == "dev"
Requires-Dist: pytest; extra == "dev"
Requires-Dist: pytest-cov; extra == "dev"
Requires-Dist: requests; extra == "dev"
Requires-Dist: setuptools; extra == "dev"
Requires-Dist: sphinx-book-theme; extra == "dev"
Requires-Dist: tox; extra == "dev"
Requires-Dist: twine; extra == "dev"
Requires-Dist: wheel; extra == "dev"
Provides-Extra: docs
Requires-Dist: sphinx-book-theme; extra == "docs"
Dynamic: license-file
